{
    "token": "726370229:AAFf-Dcw_TWzeRzRLGuKCx5XuqUetfvMWI8",
    "data": [
        {
            "teemu": [
                "True röiukko",
                "Pieni inttipoika",
                "Hakkaa kaikki mw3"
            ]
        },
        {
            "joonas": [
                "Leikkii omalla pikku Pythonillaan kotona",
                "Ei osaa ilmota fysiikan tenttiin",
                "Muuten vaan hullu poika"
            ]
        },
        {
            "osmo": [
                "Atrian kasvatti ja työukko",
                "Vähän ehkä jonne"
            ]
        },
        {
            "lassi": [
                "Kova pelaan wottia",
                "Makkarapuolen poikia",
                "Larppaa metsässä pyssyjen kanssa"
            ]
        },
        {
            "roope": [
                "Rumpalipoika",
                "Man@gerin parrakas dj",
                "Official jatkopaikka host"
            ]
        },
        {
            "toni": [
                "Hyvä pelaan guitar heroa"
            ]
        },
        {
            "petteri": [
                "Ammatiltaan laivaboliisi",
                "märkä (lapanen) laulaja",
                "Humalassa Turgusessa"
            ]
        },
        {
            "ilari": [
                "Oispa ees oikeita töitä",
                "Saispa edes tolpan..."
            ]
        },
        {
            "niklas": [
                "Marketsin uusi alpha-analyytikko",
                "Gymihirmu"
            ]
        },
        {
            "niblas": [
                "Virginity thief",
                "Not black mamba, but the white panda"
            ]
        }
    ]
}